<annotation>
	<folder>train</folder>
	<filename>images (95).jpg</filename>
	<path>C:\Users\Debjani\Anaconda3\Tensorflow\addons\labelImg\images\train\images (95).jpg</path>
	<source>
		<database>Unknown</database>
	</source>
	<size>
		<width>800</width>
		<height>600</height>
		<depth>3</depth>
	</size>
	<segmented>0</segmented>
	<object>
		<name>plastic</name>
		<pose>Unspecified</pose>
		<truncated>0</truncated>
		<difficult>0</difficult>
		<bndbox>
			<xmin>29</xmin>
			<ymin>66</ymin>
			<xmax>562</xmax>
			<ymax>516</ymax>
		</bndbox>
	</object>
	<object>
		<name>flowers</name>
		<pose>Unspecified</pose>
		<truncated>0</truncated>
		<difficult>0</difficult>
		<bndbox>
			<xmin>511</xmin>
			<ymin>435</ymin>
			<xmax>773</xmax>
			<ymax>596</ymax>
		</bndbox>
	</object>
	<object>
		<name>paper</name>
		<pose>Unspecified</pose>
		<truncated>1</truncated>
		<difficult>0</difficult>
		<bndbox>
			<xmin>659</xmin>
			<ymin>265</ymin>
			<xmax>800</xmax>
			<ymax>445</ymax>
		</bndbox>
	</object>
</annotation>
